{
  "forge_marker": 1,
  "defaults": {
    "model": "builtin/generated",
    "transform": "forge:default-item"
  },
  "variants": {
    "variant": {
      "ingot_copper": {"textures": {"layer0": "commonresources:copper/ingot"}},
      "nugget_copper": {"textures": {"layer0": "commonresources:copper/nugget"}},
      "gear_copper": {"textures": {"layer0": "commonresources:copper/gear"}},
      "dust_copper": {"textures": {"layer0": "commonresources:copper/dust"}},
      "ingot_tin": {"textures": {"layer0": "commonresources:tin/ingot"}},
      "nugget_tin": {"textures": {"layer0": "commonresources:tin/nugget"}},
      "gear_tin": {"textures": {"layer0": "commonresources:tin/gear"}},
      "dust_tin": {"textures": {"layer0": "commonresources:tin/dust"}},
      "ingot_silver": {"textures": {"layer0": "commonresources:silver/ingot"}},
      "nugget_silver": {"textures": {"layer0": "commonresources:silver/nugget"}},
      "gear_silver": {"textures": {"layer0": "commonresources:silver/gear"}},
      "dust_silver": {"textures": {"layer0": "commonresources:silver/dust"}},
      "ingot_lead": {"textures": {"layer0": "commonresources:lead/ingot"}},
      "nugget_lead": {"textures": {"layer0": "commonresources:lead/nugget"}},
      "gear_lead": {"textures": {"layer0": "commonresources:lead/gear"}},
      "dust_lead": {"textures": {"layer0": "commonresources:lead/dust"}},
      "ingot_bronze": {"textures": {"layer0": "commonresources:bronze/ingot"}},
      "nugget_bronze": {"textures": {"layer0": "commonresources:bronze/nugget"}},
      "gear_bronze": {"textures": {"layer0": "commonresources:bronze/gear"}},
      "dust_bronze": {"textures": {"layer0": "commonresources:bronze/dust"}},
      "ingot_steel": {"textures": {"layer0": "commonresources:steel/ingot"}},
      "nugget_steel": {"textures": {"layer0": "commonresources:steel/nugget"}},
      "gear_steel": {"textures": {"layer0": "commonresources:steel/gear"}},
      "dust_steel": {"textures": {"layer0": "commonresources:steel/dust"}},
      "gem_ruby": {"textures": {"layer0": "commonresources:ruby/gem"}},
      "shard_ruby": {"textures": {"layer0": "commonresources:ruby/shard"}},
      "gem_sapphire": {"textures": {"layer0": "commonresources:sapphire/gem"}},
      "shard_sapphire": {"textures": {"layer0": "commonresources:sapphire/shard"}},
      "gem_peridot": {"textures": {"layer0": "commonresources:peridot/gem"}},
      "shard_peridot": {"textures": {"layer0": "commonresources:peridot/shard"}},
      "gear_stone": {"textures": {"layer0": "commonresources:items/gear_stone"}},
      "gear_iron": {"textures": {"layer0": "commonresources:items/gear_iron"}},
      "gear_gold": {"textures": {"layer0": "commonresources:items/gear_gold"}},
      "gear_diamond": {"textures": {"layer0": "commonresources:items/gear_diamond"}},
      "dust_stone": {"textures": {"layer0": "commonresources:items/dust_stone"}},
      "dust_iron": {"textures": {"layer0": "commonresources:items/dust_iron"}},
      "dust_gold": {"textures": {"layer0": "commonresources:items/dust_gold"}},
      "dust_diamond": {"textures": {"layer0": "commonresources:items/dust_diamond"}},
      "dust_lapis": {"textures": {"layer0": "commonresources:items/dust_lapis"}},
      "rod_iron": {"textures": {"layer0": "commonresources:items/rod_iron"}}
    }
  }
}